pydoods/__init__.py
pydoods-1.0.2.dist-info/LICENSE
pydoods-1.0.2.dist-info/METADATA
pydoods-1.0.2.dist-info/WHEEL
pydoods-1.0.2.dist-info/top_level.txt
pydoods-1.0.2.dist-info/RECORD
