Metadata-Version: 2.1
Name: pydoods
Version: 1.0.2
Summary: A Python wrapper for the DOODS image detection service
Home-page: https://github.com/snowzach/pydoods
Author: Zach Brown
Author-email: doods@prozach.org
License: UNKNOWN
Platform: UNKNOWN
Classifier: Programming Language :: Python :: 3
Classifier: License :: OSI Approved :: MIT License
Classifier: Operating System :: OS Independent
